reddit/__init__.py
reddit/config.py
reddit/main.py
reddit/main_rdt.py
reddit/rdt.py
reddit/rdt_cli.py
reddit/redditcli.py
redditcli-2.1.0.dist-info/METADATA
redditcli-2.1.0.dist-info/RECORD
redditcli-2.1.0.dist-info/WHEEL
redditcli-2.1.0.dist-info/entry_points.txt
redditcli-2.1.0.dist-info/top_level.txt
