Metadata-Version: 2.1
Name: redditcli
Version: 2.1.0
Summary: A command line application that lets you browse Reddit.
Home-page: UNKNOWN
Author: Yathartha Goel
License: MIT License
Platform: Cross Platform
Classifier: Programming Language :: Python :: 3
Classifier: License :: OSI Approved :: MIT License
Classifier: Operating System :: OS Independent
Requires-Dist: click
Requires-Dist: praw
Requires-Dist: prompt-toolkit (==1.0.15)
Requires-Dist: pygments
